Combinational/encoders/_encoder8to3.v
module _encoder8to3 (
    input [7:0] in, // 8-bit input for the encoder
    output reg [2:0] out // 3-bit output for the encoder
);

// always block to implement the encoder logic
always @(*) begin
    out = 0;
    out[0] = in[7] | in[5] | in[3] | in[1]; // LSB
    out[1] = in[7] | in[6] | in[3] | in[2]; // middle bit
    out[2] = in[7] | in[6] | in[5] | in[4]; // MSB
end

endmodule

Combinational/encoders/encoder_tb.v
`timescale 1ns / 1ps
`include "_encoder8to3.v"

module encoder_tb;

reg [7:0] in; // 8 bit input for the encoder
wire [2:0] out; // 3 bit output for the encoder

_encoder8to3 e0(.in(in), .out(out)); // instantiate the encoder module

initial begin
    $dumpfile("encoder_tb.vcd"); // create a VCD file to store the simulation results
    $dumpvars(0, encoder_tb); // dump all variables in the testbench
    
    $display("Starting the testbench for _encoder8to3");
    $display("8 to 3 Encoder Testbench");

    // testcases for the 8-to-3 encoder
    $monitor("Input: %b | Output: %b", in, out); // monitor the input and output values
    in = 8'b00000001; #5;
    in = 8'b00000010; #5;
    in = 8'b00000100; #5;
    in = 8'b00001000; #5;
    in = 8'b00010000; #5;
    in = 8'b00100000; #5;
    in = 8'b01000000; #5;
    in = 8'b10000000; #5;
end
endmodule

Combinational/encoders/encoder_tb.vcd
$date
	Sat Sep 05 23:52:39 2026
$end
$version
	Icarus Verilog
$end
$timescale
	1ps
$end
$scope module encoder_tb $end
$var wire 3 ! out [2:0] $end
$var reg 8 " in [7:0] $end
$scope module e0 $end
$var wire 8 # in [7:0] $end
$var reg 3 $ out [2:0] $end
$upscope $end
$upscope $end
$enddefinitions $end
$comment Show the parameter values. $end
$dumpall
$end
#0
$dumpvars
b0 $
b1 #
b1 "
b0 !
$end
#5000
b1 !
b1 $
b10 "
b10 #
#10000
b10 !
b10 $
b100 "
b100 #
#15000
b11 !
b11 $
b1000 "
b1000 #
#20000
b100 !
b100 $
b10000 "
b10000 #
#25000
b101 !
b101 $
b100000 "
b100000 #
#30000
b110 !
b110 $
b1000000 "
b1000000 #
#35000
b111 !
b111 $
b10000000 "
b10000000 #
