Combinational/half_adder/half_adder.v
module half_adder(
    input a, // The input A
    input b, // The input B
    output sum, // The output in which the sum will be calculated
    output carry // The carry bit 
);

// Now we implement the half adder logic
assign sum = a ^ b; // The Sum is the exclusive OR of the inputs, 
assign carry = a & b; // The carry is the and of the inputs

endmodule

Combinational/full_adder/full_adder.v
`include "../half_adder/half_adder.v"
module full_adder(
    input a, 
    input b, 
    input cin, 
    output total_sum, 
    output cout
);

// Wires to hold the immediate values from the first half adder
wire sum1;
wire cout1;

// Wire to hold the c_out from the second half adder
wire cout2;

// Making a full adder out of half adders, whose output will be forwarded to the next half_adder 
half_adder ha1(.a(a), .b(b), .sum(sum1), .carry(cout1));

// Second Half Adder to combine the sum from the first half adder with the carry input
half_adder ha2(.a(cin), .b(sum1), .sum(total_sum), .carry(cout2));

// Assigning the final carry out for the full adder
assign cout = cout1 | cout2; 

endmodule

Combinational/full_adder/full_adder_tb.v
`timescale 1ns/1ps
`include "full_adder.v"

module full_adder_tb;

reg a, b, cin; // input registers for the full adder
wire sum, cout; // output wires for the full adder

// Now we instantiate the full adder module
full_adder fa(.a(a), .b(b), .cin(cin), .total_sum(sum), .cout(cout));

// Now we add the test instructions, which is the truth table for the full adder to verify operation
    initial begin

        a = 0; b = 0; cin = 0;
        #10;
        $display("Sum: %b, Carry Out: %b", sum, cout); // display the output
        
        a = 0; b = 0; cin = 1;
        #10;
        $display("Sum: %b, Carry Out: %b", sum, cout); // display the output
        
        a = 0; b = 1; cin = 0;
        #10;
        $display("Sum: %b, Carry Out: %b", sum, cout); // display the output
       
        a = 0; b = 1; cin = 1;
        #10;
        $display("Sum: %b, Carry Out: %b", sum, cout); // display the output
        a = 1; b = 0; cin = 0;
        #10;
        $display("Sum: %b, Carry Out: %b", sum, cout); // display the output
        
        a = 1; b = 0; cin = 1;
        #10;
        $display("Sum: %b, Carry Out: %b", sum, cout); // display the output
        
        a = 1; b = 1; cin = 0;
        #10;
        $display("Sum: %b, Carry Out: %b", sum, cout); // display the output

        a = 1; b = 1; cin = 1;
        #10;
        $display("Sum: %b, Carry Out: %b", sum, cout); // display the output
       
        $finish;
    end
endmodule

Combinational/full_adder/fa_waveform.vcd
$date
	Fri Sep 04 23:22:06 2026
$end
$version
	Icarus Verilog
$end
$timescale
	1ps
$end
$scope module full_adder_tb $end
$scope module fa $end
$var wire 1 ! a $end
$var wire 1 " b $end
$var wire 1 # cin $end
$var wire 1 $ cout $end
$var wire 1 % total_sum $end
$var wire 1 & sum1 $end
$var wire 1 ' cout2 $end
$var wire 1 ( cout1 $end
$scope module ha1 $end
$var wire 1 ! a $end
$var wire 1 " b $end
$var wire 1 ( carry $end
$var wire 1 & sum $end
$upscope $end
$scope module ha2 $end
$var wire 1 # a $end
$var wire 1 & b $end
$var wire 1 ' carry $end
$var wire 1 % sum $end
$upscope $end
$upscope $end
$upscope $end
$enddefinitions $end
$comment Show the parameter values. $end
$dumpall
$end
#0
$dumpvars
0(
0'
0&
0%
0$
0#
0"
0!
$end
#10000
1%
1#
#20000
1&
0#
1"
#30000
1$
0%
1'
1#
#40000
0$
1%
0'
0#
0"
1!
#50000
1$
0%
1'
1#
#60000
0'
0&
1(
0#
1"
#70000
1%
1#
