Sequential/Counters/up_down_counter.v

module counter_up_down #(parameter N = 4) (
    input clk,
    input rst,
    input dir, // direction: 1 for up, 0 for down
    output reg [N-1:0] q
);

always @(posedge clk) begin
    if (rst)
        q <= 0;
    else if(dir)
        q <= q + 1; // increment by one
    else
        q <= q - 1; // decrement by one
        
        
end

endmodule

Sequential/Counters/counter_tb.v
`timescale 1ns / 1ps
`include "up_down_counter.v"

module counter_tb;

//inputs 
reg clk = 0;
reg rst;
reg dir;

//outputs
wire [3:0] q; // for a 4 bit example

always #5 clk = ~clk; // Clock generation

//instantiate the counter
counter_up_down uut (.clk(clk), .rst(rst), .dir(dir), .q(q));

initial begin
    // Dump waveform
    $dumpfile("counter_tb.vcd");
    $dumpvars(0, counter_tb);

    //Testcases
    $display("Up - Down Counter test cases");
    $monitor("rst = %b, dir = %b, q = %d, q = %b", rst, dir, q, q);

    // clear the output 
    rst = 1; #10 rst = 0;
    dir = 1;
    #100;
    $display("\n============================================\n"); //switch to down direction
    dir = 0;
    #100;
    $finish;
end

endmodule

Sequential/Counters/counter_tb.vcd
$date
	Tue Oct 06 16:08:28 2026
$end
$version
	Icarus Verilog
$end
$timescale
	1ps
$end
$scope module counter_tb $end
$var wire 4 ! q [3:0] $end
$var reg 1 " clk $end
$var reg 1 # dir $end
$var reg 1 $ rst $end
$scope module uut $end
$var wire 1 " clk $end
$var wire 1 # dir $end
$var wire 1 $ rst $end
$var parameter 32 % N $end
$var reg 4 & q [3:0] $end
$upscope $end
$upscope $end
$enddefinitions $end
$comment Show the parameter values. $end
$dumpall
b100 %
$end
#0
$dumpvars
bx &
1$
x#
0"
bx !
$end
#5000
b0 !
b0 &
1"
#10000
0"
1#
0$
#15000
b1 !
b1 &
1"
#20000
0"
#25000
b10 !
b10 &
1"
#30000
0"
#35000
b11 !
b11 &
1"
#40000
0"
#45000
b100 !
b100 &
1"
#50000
0"
#55000
b101 !
b101 &
1"
#60000
0"
#65000
b110 !
b110 &
1"
#70000
0"
#75000
b111 !
b111 &
1"
#80000
0"
#85000
b1000 !
b1000 &
1"
#90000
0"
#95000
b1001 !
b1001 &
1"
#100000
0"
#105000
b1010 !
b1010 &
1"
#110000
0"
0#
#115000
b1001 !
b1001 &
1"
#120000
0"
#125000
b1000 !
b1000 &
1"
#130000
0"
#135000
b111 !
b111 &
1"
#140000
0"
#145000
b110 !
b110 &
1"
#150000
0"
#155000
b101 !
b101 &
1"
#160000
0"
#165000
b100 !
b100 &
1"
#170000
0"
#175000
b11 !
b11 &
1"
#180000
0"
#185000
b10 !
b10 &
1"
#190000
0"
#195000
b1 !
b1 &
1"
#200000
0"
#205000
b0 !
b0 &
1"
