Sequential/Counters/Johnson_Counter.v
`timescale 1ns / 1ps

module johnson_counter #(parameter N = 4)(
    input clk,
    input rst,
    output reg [N-1:0] q
);

always @(posedge clk) begin
    if (rst) 
        q <= 0;
    else
        q <= {q[N-2:0], ~q[N-1]}; 
end

endmodule

Sequential/Counters/jc_tb.v
`timescale 1ns / 1ps
`include "Johnson_Counter.v"

module johnson_counter_tb;

parameter N = 4;

// inputs 
reg clk = 0;
reg rst = 0;

// outputs 
wire [N-1:0] q;

// clock generation
always #10 clk = ~clk;

// instantiate the Johnson counter
johnson_counter #(.N(N)) jc0(.clk(clk), .rst(rst), .q(q));

initial begin
    
    //dump the waveform
    $dumpfile("jc_tb.vcd");
    $dumpvars(0, johnson_counter_tb);
    
    // Log
    $display("Johnson Counter Testbench");
    $monitor("q = %b, rst=%b", q, rst);

    rst = 1; #20;
    rst = 0; #200;

    $finish;
end

endmodule

Sequential/Counters/jc_tb.vcd
$date
	Wed Oct 07 19:20:21 2026
$end
$version
	Icarus Verilog
$end
$timescale
	1ps
$end
$scope module johnson_counter_tb $end
$var wire 4 ! q [3:0] $end
$var parameter 32 " N $end
$var reg 1 # clk $end
$var reg 1 $ rst $end
$scope module jc0 $end
$var wire 1 # clk $end
$var wire 1 $ rst $end
$var parameter 32 % N $end
$var reg 4 & q [3:0] $end
$upscope $end
$upscope $end
$enddefinitions $end
$comment Show the parameter values. $end
$dumpall
b100 %
b100 "
$end
#0
$dumpvars
bx &
1$
0#
bx !
$end
#10000
b0 !
b0 &
1#
#20000
0#
0$
#30000
b1 !
b1 &
1#
#40000
0#
#50000
b11 !
b11 &
1#
#60000
0#
#70000
b111 !
b111 &
1#
#80000
0#
#90000
b1111 !
b1111 &
1#
#100000
0#
#110000
b1110 !
b1110 &
1#
#120000
0#
#130000
b1100 !
b1100 &
1#
#140000
0#
#150000
b1000 !
b1000 &
1#
#160000
0#
#170000
b0 !
b0 &
1#
#180000
0#
#190000
b1 !
b1 &
1#
#200000
0#
#210000
b11 !
b11 &
1#
