Sequential/Counters/Mod_N_counter.v
module mod_n_counter #(parameter N = 2)(
    input clk,
    input rst,
    output reg [$clog2(N)-1:0] count
);

always @(posedge clk) begin
    if(rst) begin
        count <= 0;
    end else begin
        if(count == N-1) begin
            count <= 0;
        end else begin
            count <= count + 1;
        end
    end
end
endmodule

Sequential/Counters/modn_tb.v
`timescale 1ns / 1ps
`include "Mod_N_counter.v"

module modn_tb;

//inputs
localparam N = 4;
reg clk = 0;
reg rst;

//output
wire [$clog2(N)-1:0] count; // Assuming N = 8 for this testbench

//clock
always #10 clk = ~clk;

//Instantiate the module
mod_n_counter #(.N(N)) mod0 (.clk(clk), .rst(rst), .count(count));

initial begin
    //Dump the waveform for simulation
    $dumpfile("modn_tb.vcd");
    $dumpvars(0, modn_tb);

    //Log
    $display("Mod N Counter Testbench");
    $monitor("count = %d, clk = %b", count, clk);

    //Test Cases
    rst = 1; #20;
    rst = 0; #100;
    $finish;

end

endmodule

Sequential/Counters/modn_tb.vcd
$date
	Fri Oct 09 14:03:55 2026
$end
$version
	Icarus Verilog
$end
$timescale
	1ps
$end
$scope module modn_tb $end
$var wire 2 ! count [1:0] $end
$var parameter 32 " N $end
$var reg 1 # clk $end
$var reg 1 $ rst $end
$scope module mod0 $end
$var wire 1 # clk $end
$var wire 1 $ rst $end
$var parameter 32 % N $end
$var reg 2 & count [1:0] $end
$upscope $end
$upscope $end
$enddefinitions $end
$comment Show the parameter values. $end
$dumpall
b100 %
b100 "
$end
#0
$dumpvars
bx &
1$
0#
bx !
$end
#10000
b0 !
b0 &
1#
#20000
0#
0$
#30000
b1 !
b1 &
1#
#40000
0#
#50000
b10 !
b10 &
1#
#60000
0#
#70000
b11 !
b11 &
1#
#80000
0#
#90000
b0 !
b0 &
1#
#100000
0#
#110000
b1 !
b1 &
1#
