Sequential/Shift Registers/SISO.v
//SERIAL IN SERIAL OUT SHIFT REGISTER

module SISO #(parameter N = 1)(
    input d,
    input clk,
    input rst,
    output q,
    output [N-1:0] shift_reg_out
);

reg [N-1:0] shift_reg;

always @(posedge clk) begin
    if(rst)
        shift_reg <= 0; // reset behaviour
    else if (N==1)
        shift_reg <= d; // if N == 1 then make it a simple D flip flop 
    else
        shift_reg <= {shift_reg[N-2:0], d}; // shift the values ahead 
end

assign q = shift_reg[N-1]; // assign the q as the value of the last shift reg
assign shift_reg_out = shift_reg; // assign the output register values
endmodule

Sequential/Counters/Ring_counter.v
`timescale 1ns / 1ps
`include "../Shift Registers/SISO.v"

module ring_counter #(parameter N = 4)(
    input preset,
    input clk,
    input rst,
    output reg [N-1:0] q
);

// To assign one to the first flip-flop when preset is high,
// otherwise take the value from the last flip-flop

always @(posedge clk) begin
    if (rst) begin
        q <= 0;
    end else if (preset) begin
        q[0] <= 1;
    end else begin
        q <= {q[N-2:0], q[N-1]};
    end
end
endmodule

Sequential/Counters/ring_counter_tb.v
`timescale 1ns / 1ps
`include "Ring_counter.v"

module ring_counter_tb;

parameter N = 4;

//inputs
reg preset = 0;
reg clk = 0;
reg rst = 0;

// output
wire [N-1:0] q;

// clock generation
always #10 clk = ~clk;

// Now we instantiate the ring counter
ring_counter #(N) rc0(.preset(preset), .clk(clk), .rst(rst), .q(q));

initial begin

    // Dump waveform
    $dumpfile("ring_counter_tb.vcd");
    $dumpvars(0, ring_counter_tb);

    // Log
    $display("Ring Counter Testbench");
    $monitor("Ring Counter Output: q=%b, preset=%b, rst=%b", q, preset, rst);
    rst = 1; #20;
    rst = 0; #20;

    preset = 1; #20;
    preset = 0; #100;
    
    $finish;
end

endmodule

Sequential/Counters/ring_counter_tb.vcd
$date
	Wed Oct 07 14:07:15 2026
$end
$version
	Icarus Verilog
$end
$timescale
	1ps
$end
$scope module ring_counter_tb $end
$var wire 4 ! q [3:0] $end
$var parameter 32 " N $end
$var reg 1 # clk $end
$var reg 1 $ preset $end
$var reg 1 % rst $end
$scope module rc0 $end
$var wire 1 # clk $end
$var wire 1 $ preset $end
$var wire 1 % rst $end
$var parameter 32 & N $end
$var reg 4 ' q [3:0] $end
$upscope $end
$upscope $end
$enddefinitions $end
$comment Show the parameter values. $end
$dumpall
b100 &
b100 "
$end
#0
$dumpvars
bx '
1%
0$
0#
bx !
$end
#10000
b0 !
b0 '
1#
#20000
0#
0%
#30000
1#
#40000
0#
1$
#50000
b1 !
b1 '
1#
#60000
0#
0$
#70000
b10 !
b10 '
1#
#80000
0#
#90000
b100 !
b100 '
1#
#100000
0#
#110000
b1000 !
b1000 '
1#
#120000
0#
#130000
b1 !
b1 '
1#
#140000
0#
#150000
b10 !
b10 '
1#
