Sequential/SR_Latch/SR_Latch.v
`timescale 1ps/1ps
module SR_Latch(
    input set, // the set input for the latch
    input reset, // the reset input for the latch 
    
    output Q,    // the output value for the latch
    output Qn    // the output value for the latch
);

nor(Q, reset, Qn); // Q here is the result of NOR of reset and Qbar
nor(Qn, set, Q); // Qn here is the result of NOR of set and Q


endmodule

Sequential/D/D_latch.v
`include "../SR_Latch/SR_Latch.v"

// Modelling a D latch
module D_latch(
    input D,        //input variable 
    input enable,   // enable input for the latch
    output Qbar,    // output bar value
    output Q       // output value
);

//inputs that will go into a SR_latch
wire set = D & enable;
wire reset = ~D & enable; //This ensures that the S and R input are always opposite 

//instantiate the SR latch so we can connect it 
SR_Latch s0(.set(set), .reset(reset), .Q(Q), .Qn(Qbar));

endmodule

Sequential/Flip Flop/D_Flip_Flop.v
// to build off of D Latch
`include "../D/D_latch.v"

module d_flip_flop(
    input D,        // input data
    input clk,      // the clock
    output Q,       // the output
    output Qbar     // the opposite of output 
);

wire Q_carry; // this will carry the Q from Master D latch to slave d latch

D_latch d0(.D(D), .enable(~clk), .Q(Q_carry)); // Master D latch

D_latch d1(.D(Q_carry), .enable(clk), .Q(Q), .Qbar(Qbar)); // Slave D latch

endmodule

Sequential/Flip Flop/D_ff_tb.v
`timescale 1ns/1ps
`include "D_Flip_Flop.v"

module d_ff_tb;

//inputs 
reg D;
reg clk = 0; //intial condition for the clock

//outputs
wire Q;
wire Qbar;

//Instantiate the D flip flop
d_flip_flop dff0(.D(D), .clk(clk), .Q(Q), .Qbar(Qbar));

always #10 clk = ~clk;

initial begin
    
    //Getting the waveforms
    $dumpfile("d_ff.vcd");
    $dumpvars(0, d_ff_tb);

    // Debugging the dff
    $display("Testing the D Flip Flop");
    $monitor("D:%b, CLK:%b | Q:%b, ~Q:%b", D, clk, Q, Qbar);
    
    // Testcases
    D = 0; #20;
    D = 1; #20;
    D = 0; #20;
    D = 1; #20;

    $finish;
end

endmodule

Sequential/Flip Flop/d_ff.vcd
$date
	Fri Oct 02 13:25:54 2026
$end
$version
	Icarus Verilog
$end
$timescale
	1ps
$end
$scope module d_ff_tb $end
$var wire 1 ! Qbar $end
$var wire 1 " Q $end
$var reg 1 # D $end
$var reg 1 $ clk $end
$scope module dff0 $end
$var wire 1 # D $end
$var wire 1 $ clk $end
$var wire 1 ! Qbar $end
$var wire 1 % Q_carry $end
$var wire 1 " Q $end
$scope module d0 $end
$var wire 1 # D $end
$var wire 1 & enable $end
$var wire 1 ' reset $end
$var wire 1 ( set $end
$var wire 1 ) Qbar $end
$var wire 1 % Q $end
$scope module s0 $end
$var wire 1 % Q $end
$var wire 1 ) Qn $end
$var wire 1 ' reset $end
$var wire 1 ( set $end
$upscope $end
$upscope $end
$scope module d1 $end
$var wire 1 % D $end
$var wire 1 $ enable $end
$var wire 1 * reset $end
$var wire 1 + set $end
$var wire 1 ! Qbar $end
$var wire 1 " Q $end
$scope module s0 $end
$var wire 1 " Q $end
$var wire 1 ! Qn $end
$var wire 1 * reset $end
$var wire 1 + set $end
$upscope $end
$upscope $end
$upscope $end
$upscope $end
$enddefinitions $end
$comment Show the parameter values. $end
$dumpall
$end
#0
$dumpvars
0+
0*
1)
0(
1'
1&
0%
0$
0#
x"
x!
$end
#10
1!
0'
0"
0&
1*
1$
#20
1%
0)
1(
1&
0*
0$
1#
#30
1"
0(
0!
0&
1+
1$
#40
1)
0%
1'
1&
0+
0$
0#
#50
1!
0'
0"
0&
1*
1$
#60
1%
0)
1(
1&
0*
0$
1#
#70
1"
0(
0!
0&
1+
1$
#80
1(
1&
0+
0$
