Sequential/Flip Flop/JK_ff.v
module jk_ff (
    //input variables
    input clk,
    input J,
    input K,
    input rst,

    //output variables
    output reg Q,
    output Qbar
);

// make it trigger on the positive edge of the clock, this is the synchronous version
always @(posedge clk) begin
    if(rst) begin
        Q <= 0;
    end else begin
        // all the cases for the JK flip-flop
        case ({J, K})
            2'b00: Q <= Q;
            2'b01: Q <= 0;
            2'b10: Q <= 1;
            2'b11: Q <= ~Q;
        endcase
end
end

assign Qbar = ~Q; // since they should be complementary

endmodule

Sequential/Flip Flop/jkff_tb.v
`timescale 1ns/1ps
`include "JK_ff.v"

module jkff_tb;

//inputs 
reg J;
reg K;
reg rst;
reg clk = 0;

//output variables
wire Q;
wire Qbar;

always #10 clk = ~clk;

jk_ff j0(.J(J), .K(K), .rst(rst), .clk(clk), .Q(Q), .Qbar(Qbar));

initial begin
    // dump the waveforms for debugging
    $dumpfile("jk_ff.vcd");
    $dumpvars(0, jkff_tb);

    $display("Testing the JK Flip-Flop");
    $monitor("J = %b, K = %b, rst = %b, clk = %b, Q = %b, Qbar = %b", J, K, rst, clk, Q, Qbar);
    //test cases
    
    J = 0; K = 0; rst = 0; #20;
    J = 0; K = 0; rst = 1; #20;
    J = 0; K = 0; rst = 0; #20;
    J = 0; K = 0; rst = 0; #20;
    J = 0; K = 1; rst = 0; #20;
    J = 1; K = 0; rst = 0; #20;
    J = 1; K = 1; rst = 0; #20;

    $finish;
end

endmodule

Sequential/Flip Flop/jk_ff.vcd
$date
	Fri Oct 02 13:57:57 2026
$end
$version
	Icarus Verilog
$end
$timescale
	1ps
$end
$scope module jkff_tb $end
$var wire 1 ! Qbar $end
$var wire 1 " Q $end
$var reg 1 # J $end
$var reg 1 $ K $end
$var reg 1 % clk $end
$var reg 1 & rst $end
$scope module j0 $end
$var wire 1 # J $end
$var wire 1 $ K $end
$var wire 1 ! Qbar $end
$var wire 1 % clk $end
$var wire 1 & rst $end
$var reg 1 " Q $end
$upscope $end
$upscope $end
$enddefinitions $end
$comment Show the parameter values. $end
$dumpall
$end
#0
$dumpvars
0&
0%
0$
0#
x"
x!
$end
#10000
1%
#20000
0%
1&
#30000
1!
0"
1%
#40000
0%
0&
#50000
1%
#60000
0%
#70000
1%
#80000
0%
1$
#90000
1%
#100000
0%
0$
1#
#110000
0!
1"
1%
#120000
0%
1$
#130000
1!
0"
1%
