Sequential/SR_Latch/SR_Latch.v
`timescale 1ps/1ps
module SR_Latch(
    input set, // the set input for the latch
    input reset, // the reset input for the latch 
    
    output Q,    // the output value for the latch
    output Qn    // the output value for the latch
);

nor(Q, reset, Qn); // Q here is the result of NOR of reset and Qbar
nor(Qn, set, Q); // Qn here is the result of NOR of set and Q


endmodule

Sequential/D/D_latch.v
`include "../SR_Latch/SR_Latch.v"

// Modelling a D latch
module D_latch(
    input D,        //input variable 
    input enable,   // enable input for the latch
    output Qbar,    // output bar value
    output Q       // output value
);

//inputs that will go into a SR_latch
wire set = D & enable;
wire reset = ~D & enable; //This ensures that the S and R input are always opposite 

//instantiate the SR latch so we can connect it 
SR_Latch s0(.set(set), .reset(reset), .Q(Q), .Qn(Qbar));

endmodule

Sequential/Flip Flop/D_Flip_Flop.v
// to build off of D Latch
`include "../D/D_latch.v"

module d_flip_flop(
    input D,        // input data
    input clk,      // the clock
    output Q,       // the output
    output Qbar     // the opposite of output 
);

wire Q_carry; // this will carry the Q from Master D latch to slave d latch

D_latch d0(.D(D), .enable(~clk), .Q(Q_carry)); // Master D latch

D_latch d1(.D(Q_carry), .enable(clk), .Q(Q), .Qbar(Qbar)); // Slave D latch

endmodule

Sequential/Flip Flop/T_flip_flop.v
`include "D_Flip_Flop.v"

module t_flip_flop(
    input T,        // the toggle input
    input clk,      // the clock signal
    input rst,
    output Q,       // the Q signal
    output Qbar     // the Qbar signal
);

wire D;             // carrying the combined XOR 

assign D = (T ^ Q) & ~rst; // Just need to add an XOR gate with synchronous reset so Q isn't stuck in x

// Instantiate a d flip flop 
d_flip_flop dff0(.D(D), .clk(clk), .Q(Q), .Qbar(Qbar));

endmodule

Sequential/Flip Flop/tff_tb.v
`timescale 1ns/1ps
`include "T_Flip_Flop.v"

module tff_tb;

// Inputs
reg T;
reg rst;

//Outputs
wire Q;
wire Qbar;

//intial value for clk
reg clk = 0;

//Instantiate the tflip flop
t_flip_flop tff0(.T(T), .clk(clk), .Q(Q), .Qbar(Qbar), .rst(rst));

always #10 clk = ~clk;

initial begin

    //dump the waveforms for debugging 
    $dumpfile("t_ff.vcd");
    $dumpvars(0, tff_tb);

    $display("Testing the T Flip Flop");
    $monitor("T:%b, Q:%b", T, Q);

    rst = 1; T = 1'b0; #20; // to reset the intial x state 
    rst = 0; 
    
    T = 1; #20;
    T = 0; #20;
    T = 1; #20;
    T = 0; #20;
    $finish;
end

endmodule

Sequential/Flip Flop/t_ff.vcd
$date
	Fri Oct 02 13:53:22 2026
$end
$version
	Icarus Verilog
$end
$timescale
	1ps
$end
$scope module tff_tb $end
$var wire 1 ! Qbar $end
$var wire 1 " Q $end
$var reg 1 # T $end
$var reg 1 $ clk $end
$var reg 1 % rst $end
$scope module tff0 $end
$var wire 1 & D $end
$var wire 1 # T $end
$var wire 1 $ clk $end
$var wire 1 % rst $end
$var wire 1 ! Qbar $end
$var wire 1 " Q $end
$scope module dff0 $end
$var wire 1 & D $end
$var wire 1 $ clk $end
$var wire 1 ! Qbar $end
$var wire 1 ' Q_carry $end
$var wire 1 " Q $end
$scope module d0 $end
$var wire 1 & D $end
$var wire 1 ( enable $end
$var wire 1 ) reset $end
$var wire 1 * set $end
$var wire 1 + Qbar $end
$var wire 1 ' Q $end
$scope module s0 $end
$var wire 1 ' Q $end
$var wire 1 + Qn $end
$var wire 1 ) reset $end
$var wire 1 * set $end
$upscope $end
$upscope $end
$scope module d1 $end
$var wire 1 ' D $end
$var wire 1 $ enable $end
$var wire 1 , reset $end
$var wire 1 - set $end
$var wire 1 ! Qbar $end
$var wire 1 " Q $end
$scope module s0 $end
$var wire 1 " Q $end
$var wire 1 ! Qn $end
$var wire 1 , reset $end
$var wire 1 - set $end
$upscope $end
$upscope $end
$upscope $end
$upscope $end
$upscope $end
$enddefinitions $end
$comment Show the parameter values. $end
$dumpall
$end
#0
$dumpvars
0-
0,
1+
0*
1)
1(
0'
0&
1%
0$
0#
x"
x!
$end
#10
1!
0)
0"
0(
1,
1$
#20
1'
0+
1*
0)
1&
1(
0,
0$
1#
0%
#30
0&
1"
0*
0!
0(
1-
1$
#40
1'
1*
0)
1&
1(
0-
0$
0#
#50
0*
0(
1-
1$
#60
1+
0'
1)
0&
1(
0-
0$
1#
#70
1&
1!
0)
0"
0(
1,
1$
#80
1)
0&
1(
0,
0$
0#
#90
0)
0(
1,
1$
#100
1)
1(
0,
0$
