encoders/priorityEn8_3.v
module priorityEn8_3 (
    input      [7:0] in,     // 8 request lines
    output reg [2:0] out    // index of highest set bit
);

    // take the highest set bit 
    always @(*) begin
        casez (in)
            8'b1???????: out = 3'd7;
            8'b01??????: out = 3'd6;
            8'b001?????: out = 3'd5;
            8'b0001????: out = 3'd4;
            8'b00001???: out = 3'd3;
            8'b000001??: out = 3'd2;
            8'b0000001?: out = 3'd1;
            default:     out = 3'd0;
        endcase
    end

endmodule

encoders/priority_tb.v
`timescale 1ns/1ps
`include "priorityEn8_3.v"

module priority_tb;

// testcases for the 8-to-3 priority encoder
reg [7:0] in; // 8-bit input for the encoder
wire [2:0] out; // 3-bit output for the encoder

priorityEn8_3 p0(.in(in), .out(out)); // instantiate the priority encoder module

    initial begin
        $dumpfile("priority_tb.vcd"); // create a VCD file to store the simulation results
        $dumpvars(0, priority_tb); // dump all variables in the testbench
        
        $display("Starting the testbench for priority_encoder");
        $display("8 to 3 Priority Encoder Testbench");

        $monitor("Input: %b | Output: %b", in, out); // monitor the input and output values
        in = 8'b10000001; #5;
        in = 8'b00000010; #5;
        in = 8'b01000100; #5;
        in = 8'b00001010; #5;
        in = 8'b00010000; #5;
        in = 8'b00100000; #5;
        in = 8'b01000000; #5;
        in = 8'b00000000; #5;
    end
endmodule

encoders/priority_tb.vcd
$date
	Sat Sep 05 23:53:04 2026
$end
$version
	Icarus Verilog
$end
$timescale
	1ps
$end
$scope module priority_tb $end
$var wire 3 ! out [2:0] $end
$var reg 8 " in [7:0] $end
$scope module p0 $end
$var wire 8 # in [7:0] $end
$var reg 3 $ out [2:0] $end
$upscope $end
$upscope $end
$enddefinitions $end
$comment Show the parameter values. $end
$dumpall
$end
#0
$dumpvars
b111 $
b10000001 #
b10000001 "
b111 !
$end
#5000
b1 !
b1 $
b10 "
b10 #
#10000
b110 !
b110 $
b1000100 "
b1000100 #
#15000
b11 !
b11 $
b1010 "
b1010 #
#20000
b100 !
b100 $
b10000 "
b10000 #
#25000
b101 !
b101 $
b100000 "
b100000 #
#30000
b110 !
b110 $
b1000000 "
b1000000 #
#35000
b0 !
b0 $
b0 "
b0 #
