Combinational/demuxes/demux_1to2.v
`ifndef DMUX_1TO2_V
`define DMUX_1TO2_V
module dmux_1to2(
    input a, // input to the demux
    input sel, // selection input
    output reg out0, // output 0
    output reg out1 // output 1
);

always @(*) begin
    if(sel == 1'b0) begin
        out0 = a; // if sel is 0 then output 0 will be a
        out1 = 1'b0; // output 1 will be 0
    end else begin
        out0 = 1'b0; // output 0 will be 0
        out1 = a; // if sel is 1 then output 1 will be a
    end
end
endmodule
`endif

Combinational/demuxes/demux_1to4.v
`include "demux_1to2.v"

`ifndef DMUX_1TO4_V
`define DMUX_1TO4_V

module dmux_1to4(
    input a, // input to the demux
    input [1:0] sel, // selection input
    output [3:0] out // outputs 0-3
);

wire carry0, carry1; // wires to connect the two 1 to 2 demuxes

// using 3, 1 to 2 demuxes to implement a 1 to 4 demux
dmux_1to2 d1(.a(a), .sel(sel[0]), .out0(carry0), .out1(carry1));
dmux_1to2 d2(.a(carry0), .sel(sel[1]), .out0(out[0]), .out1(out[1]));
dmux_1to2 d3(.a(carry1), .sel(sel[1]), .out0(out[2]), .out1(out[3]));  

endmodule
`endif

Combinational/demuxes/demux_1to8.v
`include "demux_1to4.v"

`ifndef DMUX_1TO8_V
`define DMUX_1TO8_V

module dmux_1to8(
    input a, // input to the demux
    input [2:0] sel, // selection input
    output [7:0] out // outputs 0-7
);

wire carry1, carry2; // wires to connect the 1 to 4 demuxes

// using 3, 1 to 4 demuxes to implement a 1 to 8 demux
dmux_1to2 d1(.a(a), .sel(sel[2]), .out0(carry1), .out1(carry2));
dmux_1to4 d2(.a(carry1), .sel(sel[1:0]), .out(out[3:0]));
dmux_1to4 d3(.a(carry2), .sel(sel[1:0]), .out(out[7:4]));

endmodule
`endif

Combinational/demuxes/demux_tb.v
`timescale 1ps/1ps
`include "demux_1to2.v" // include the demux module
`include "demux_1to4.v" // include the demux module
`include "demux_1to8.v" // include the demux module

module demux_tb;

// variables for 1 to 2 demux
reg a; // input to the demux
reg sel; // selection input
wire [1:0] out; // outputs

//vairables for 1 to 4 demux
reg b; // input to the demux
reg [1:0] sel4; // selection input
wire [3:0] out4; // outputs

//variables for 1 to 8 demux
reg c; // input to the demux
reg [2:0] sel8; // selection input
wire [7:0] out8; // outputs

// instantiate the demuxs
dmux_1to2 d1(.a(a), .sel(sel), .out0(out[0]), .out1(out[1]));
dmux_1to4 d2(.a(b), .sel(sel4), .out(out4));
dmux_1to8 d3(.a(c), .sel(sel8), .out(out8));

initial begin
    // dump waveform for debugging
    $dumpfile("demux.vcd");
    $dumpvars(0, demux_tb);

    $display("Testing 1 to 2 demux");
    $monitor("a=%b sel=%b | out=%b", a, sel, out);
    a = 1'b0; sel = 1'b0; #5;
    a = 1'b1; sel = 1'b0; #5;
    a = 1'b0; sel = 1'b1; #5;
    a = 1'b1; sel = 1'b1; #5;

    $display("\nTesting 1 to 4 demux");
    $monitor("b=%b sel4=%b | out4=%b", b, sel4, out4);
    b = 1'b0; sel4 = 2'b00; #5;
    b = 1'b1; sel4 = 2'b00; #5;
    b = 1'b0; sel4 = 2'b01; #5;
    b = 1'b1; sel4 = 2'b01; #5;
    b = 1'b0; sel4 = 2'b10; #5;
    b = 1'b1; sel4 = 2'b10; #5;
    b = 1'b0; sel4 = 2'b11; #5;
    b = 1'b1; sel4 = 2'b11; #5;

    $display("\nTesting 1 to 8 demux");
    $monitor("c=%b sel8=%b | out8=%b", c, sel8, out8);
    c = 1'b0; sel8 = 3'b000; #5;
    c = 1'b1; sel8 = 3'b000; #5;
    c = 1'b0; sel8 = 3'b001; #5;
    c = 1'b1; sel8 = 3'b001; #5;
    c = 1'b0; sel8 = 3'b010; #5;
    c = 1'b1; sel8 = 3'b010; #5;
    c = 1'b0; sel8 = 3'b011; #5;
    c = 1'b1; sel8 = 3'b011; #5;
    c = 1'b0; sel8 = 3'b100; #5;
    c = 1'b1; sel8 = 3'b100; #5;
    c = 1'b0; sel8 = 3'b101; #5;
    c = 1'b1; sel8 = 3'b101; #5;
    c = 1'b0; sel8 = 3'b110; #5;
    c = 1'b1; sel8 = 3'b110; #5;
    c = 1'b0; sel8 = 3'b111; #5;
    c = 1'b1; sel8 = 3'b111; #5;

    $finish;
end

endmodule

Combinational/demuxes/demux.vcd
$date
	Sat Sep 05 13:13:30 2026
$end
$version
	Icarus Verilog
$end
$timescale
	1ps
$end
$scope module demux_tb $end
$var wire 8 ! out8 [7:0] $end
$var wire 4 " out4 [3:0] $end
$var wire 2 # out [1:0] $end
$var reg 1 $ a $end
$var reg 1 % b $end
$var reg 1 & c $end
$var reg 1 ' sel $end
$var reg 2 ( sel4 [1:0] $end
$var reg 3 ) sel8 [2:0] $end
$scope module d1 $end
$var wire 1 $ a $end
$var wire 1 ' sel $end
$var reg 1 * out0 $end
$var reg 1 + out1 $end
$upscope $end
$scope module d2 $end
$var wire 1 % a $end
$var wire 2 , sel [1:0] $end
$var wire 4 - out [3:0] $end
$var wire 1 . carry1 $end
$var wire 1 / carry0 $end
$scope module d1 $end
$var wire 1 % a $end
$var wire 1 0 sel $end
$var reg 1 / out0 $end
$var reg 1 . out1 $end
$upscope $end
$scope module d2 $end
$var wire 1 / a $end
$var wire 1 1 sel $end
$var reg 1 2 out0 $end
$var reg 1 3 out1 $end
$upscope $end
$scope module d3 $end
$var wire 1 . a $end
$var wire 1 4 sel $end
$var reg 1 5 out0 $end
$var reg 1 6 out1 $end
$upscope $end
$upscope $end
$scope module d3 $end
$var wire 1 & a $end
$var wire 3 7 sel [2:0] $end
$var wire 8 8 out [7:0] $end
$var wire 1 9 carry2 $end
$var wire 1 : carry1 $end
$scope module d1 $end
$var wire 1 & a $end
$var wire 1 ; sel $end
$var reg 1 : out0 $end
$var reg 1 9 out1 $end
$upscope $end
$scope module d2 $end
$var wire 1 : a $end
$var wire 2 < sel [1:0] $end
$var wire 4 = out [3:0] $end
$var wire 1 > carry1 $end
$var wire 1 ? carry0 $end
$scope module d1 $end
$var wire 1 : a $end
$var wire 1 @ sel $end
$var reg 1 ? out0 $end
$var reg 1 > out1 $end
$upscope $end
$scope module d2 $end
$var wire 1 ? a $end
$var wire 1 A sel $end
$var reg 1 B out0 $end
$var reg 1 C out1 $end
$upscope $end
$scope module d3 $end
$var wire 1 > a $end
$var wire 1 D sel $end
$var reg 1 E out0 $end
$var reg 1 F out1 $end
$upscope $end
$upscope $end
$scope module d3 $end
$var wire 1 9 a $end
$var wire 2 G sel [1:0] $end
$var wire 4 H out [3:0] $end
$var wire 1 I carry1 $end
$var wire 1 J carry0 $end
$scope module d1 $end
$var wire 1 9 a $end
$var wire 1 K sel $end
$var reg 1 J out0 $end
$var reg 1 I out1 $end
$upscope $end
$scope module d2 $end
$var wire 1 J a $end
$var wire 1 L sel $end
$var reg 1 M out0 $end
$var reg 1 N out1 $end
$upscope $end
$scope module d3 $end
$var wire 1 I a $end
$var wire 1 O sel $end
$var reg 1 P out0 $end
$var reg 1 Q out1 $end
$upscope $end
$upscope $end
$upscope $end
$upscope $end
$enddefinitions $end
$comment Show the parameter values. $end
$dumpall
$end
#0
$dumpvars
xQ
xP
xO
xN
xM
xL
xK
xJ
xI
bx H
bx G
xF
xE
xD
xC
xB
xA
x@
x?
x>
bx =
bx <
x;
x:
x9
bx 8
bx 7
x6
x5
x4
x3
x2
x1
x0
x/
x.
bx -
bx ,
0+
0*
bx )
bx (
0'
x&
x%
0$
b0 #
bx "
bx !
$end
#5
b1 #
1*
1$
#10
b0 #
0*
1'
0$
#15
b10 #
1+
1$
#20
06
05
03
b0 "
b0 -
02
00
01
04
0.
0/
b0 (
b0 ,
0%
#25
b1 "
b1 -
12
1/
1%
#30
b0 "
b0 -
02
10
0/
b1 (
b1 ,
0%
#35
b100 "
b100 -
15
1.
1%
#40
b0 "
b0 -
05
00
11
14
0.
b10 (
b10 ,
0%
#45
b10 "
b10 -
13
1/
1%
#50
b0 "
b0 -
03
10
0/
b11 (
b11 ,
0%
#55
b1000 "
b1000 -
16
1.
1%
#60
0Q
0P
0N
b0 H
0M
0F
0E
0C
b0 !
b0 8
b0 =
0B
0@
0A
0D
0K
0L
0O
0I
0J
0>
0?
0;
b0 <
b0 G
09
0:
b0 )
b0 7
0&
#65
b1 !
b1 8
b1 =
1B
1?
1:
1&
#70
b0 !
b0 8
b0 =
0B
1@
1K
0?
b1 <
b1 G
0:
b1 )
b1 7
0&
#75
b100 !
b100 8
b100 =
1E
1>
1:
1&
#80
b0 !
b0 8
b0 =
0E
0@
1A
1D
0K
1L
1O
0>
b10 <
b10 G
0:
b10 )
b10 7
0&
#85
b10 !
b10 8
b10 =
1C
1?
1:
1&
#90
b0 !
b0 8
b0 =
0C
1@
1K
0?
b11 <
b11 G
0:
b11 )
b11 7
0&
#95
b1000 !
b1000 8
b1000 =
1F
1>
1:
1&
#100
b0 !
b0 8
b0 =
0F
0@
0A
0D
0K
0L
0O
0>
1;
b0 <
b0 G
0:
b100 )
b100 7
0&
#105
b10000 !
b10000 8
b1 H
1M
1J
19
1&
#110
b0 !
b0 8
b0 H
0M
1@
1K
0J
b1 <
b1 G
09
b101 )
b101 7
0&
#115
b1000000 !
b1000000 8
b100 H
1P
1I
19
1&
#120
b0 !
b0 8
b0 H
0P
0@
1A
1D
0K
1L
1O
0I
b10 <
b10 G
09
b110 )
b110 7
0&
#125
b100000 !
b100000 8
b10 H
1N
1J
19
1&
#130
b0 !
b0 8
b0 H
0N
1@
1K
0J
b11 <
b11 G
09
b111 )
b111 7
0&
#135
b10000000 !
b10000000 8
b1000 H
1Q
1I
19
1&
