Combinational/barrel_shifter/barrel_shifter.v
module barrel_shifter(
    input [7:0] in, // 8 bit input for the shifter
    input [2:0] shifting, // shift amount 

    output [7:0] out_shifted // shifted output 
);

wire [7:0] out0, out1; // wires to carry the value through

assign out0 = shifting[0] ? {in[6:0], 1'b0} : in; // we shift this by 1
assign out1 = shifting[1] ? {out0[5:0], 2'b00} : out0; // we shift this by 2 
assign out_shifted = shifting[2] ? {out1[4:0], 4'b0000} : out1; // we shift this by 4

endmodule

barrel_shifter/barrelshifter_tb.v
`timescale 1ps/1ps
`include "barrel_shifter.v"

module barrelshifter_tb;

    reg [7:0] in; // 8 bit input for the shifter 
    reg [2:0] shift_amt; // amount to shift by 
    
    wire [7:0] result; // the shifted output 

    integer i; // index variable for the for loop

    //instantiate the barrel shifter module
    barrel_shifter b0(.in(in), .shifting(shift_amt), .out_shifted(result));

    initial begin 
        
        // Generating VCDD for testbench and debugging 
        $dumpfile("barrel.vcd");
        $dumpvars(0, barrelshifter_tb);

        // a testcase 8 bit number 
        in = 8'b00000001;
        $display("in = %b", in);

        // for loop for running the verification
        for (i = 0; i < 8; i = i + 1) begin
            shift_amt = i; 
            #5;

            // This will display the shift to verify against the expected shift
            $display("shift=%0d | out=%b  (expected %b)", i, result, (8'b00000001 << i));
        end

        // a second pattern, to see the bits that will get discarded 
        in = 8'b10110010; shift_amt = 3'd3; 
        #5;
        
        $display("\nin=%b shift=3 | out=%b  (expected %b)", in, result, (8'b10110010 << 3));

        $finish;
    end
endmodule

barrel_shifter/barrel.vcd
$date
	Mon Sep 07 20:37:05 2026
$end
$version
	Icarus Verilog
$end
$timescale
	1ps
$end
$scope module barrelshifter_tb $end
$var wire 8 ! result [7:0] $end
$var reg 8 " in [7:0] $end
$var reg 3 # shift_amt [2:0] $end
$var integer 32 $ i [31:0] $end
$scope module b0 $end
$var wire 8 % in [7:0] $end
$var wire 3 & shifting [2:0] $end
$var wire 8 ' out_shifted [7:0] $end
$var wire 8 ( out1 [7:0] $end
$var wire 8 ) out0 [7:0] $end
$upscope $end
$upscope $end
$enddefinitions $end
$comment Show the parameter values. $end
$dumpall
$end
#0
$dumpvars
b1 )
b1 (
b1 '
b0 &
b1 %
b0 $
b0 #
b1 "
b1 !
$end
#5
b10 !
b10 '
b10 (
b10 )
b1 #
b1 &
b1 $
#10
b100 !
b100 '
b1 )
b100 (
b10 #
b10 &
b10 $
#15
b1000 !
b1000 '
b1000 (
b10 )
b11 #
b11 &
b11 $
#20
b10000 !
b10000 '
b1 )
b1 (
b100 #
b100 &
b100 $
#25
b100000 !
b100000 '
b10 (
b10 )
b101 #
b101 &
b101 $
#30
b1000000 !
b1000000 '
b1 )
b100 (
b110 #
b110 &
b110 $
#35
b10000000 !
b10000000 '
b1000 (
b10 )
b111 #
b111 &
b111 $
#40
b10010000 (
b10010000 !
b10010000 '
b1100100 )
b11 #
b11 &
b10110010 "
b10110010 %
b1000 $
