Combinational/muxes/8to1.v
// Implementing a 8 to 1 mux 
module mux_8to1(
    input [7:0] a, // normal inputs
    input [2:0] sel, // the selection input is a 3 bit wide input
    output reg out // output 
);

// always block for the 8 to 1 mux, it will check the value of sel and assign the corresponding input to the output
always @(*) begin
    case(sel)
        3'b000 : out = a[0]; 
        3'b001 : out = a[1]; 
        3'b010 : out = a[2]; 
        3'b011 : out = a[3]; 
        3'b100 : out = a[4]; 
        3'b101 : out = a[5]; 
        3'b110 : out = a[6]; 
        3'b111 : out = a[7]; 
    endcase
end
endmodule

Combinational/muxes/4to1.v
// Implementing a 4 to 1 mux 
module mux_4to1(
    input [3:0] a, // normal inputs
    input [1:0] sel, // the selection input is a 2 bit wide input
    output reg out // output 
);

always @(*) begin
    case(sel)
        2'b00 : out = a[0]; // if sel is 00 then output will be a[0]
        2'b01 : out = a[1]; // if sel is 01 then output will be a[1]
        2'b10 : out = a[2]; // if sel is 10 then output will be a[2]
        2'b11 : out = a[3]; // if sel is 11 then output will be a[3]
    endcase
end
endmodule

Combinational/muxes/2to1.v
// Implementing a 2 to 1 mux 
module mux_2to1(
    input a,
    input b, // normal inputs
    input sel, // the selection input
    output out // output 
);

 // if sel is 1 then output will be b else output will be a
assign out = sel ? b : a; 

endmodule

Combinational/muxes/muxstb.v
`timescale 1ns / 1ps
`include "../muxes/2to1.v" // include the 2 to 1 mux module
`include "../muxes/4to1.v" // include the 4 to 1 mux module
`include "../muxes/8to1.v" // include the 8 to 1 mux module

module muxtb;

reg [1:0] a = 2'b01; // input for 2 to 1 mux 
reg sel; //selection input for 2 to 1 mux

reg [3:0] b = 4'b0101; // input for 4 to 1 mux
reg [1:0] sel4; //selection input for 4 to 1 mux


reg [7:0] c = 8'b01010101; // input for 8 to 1 mux
reg [2:0] sel8; //selection input for 8 to 1 mux

wire out1, out2, out3; // output bit for muxes

mux_2to1 m0(.a(a[0]), .b(a[1]), .sel(sel), .out(out1)); // instantiate the 2 to 1 mux

mux_4to1 m1(.a(b), .sel(sel4), .out(out2)); // instantiate the 4 to 1 mux

mux_8to1 m2(.a(c), .sel(sel8), .out(out3)); // instantiate the 8 to 1 mux


initial begin 

    $dumpfile("muxes.vcd");
    $dumpvars(0, muxtb);
    
    $display("Testing 2 to 1 mux");
    sel = 1'b0; 
    #5; // select a[0]
    $display("sel=%b === out=%b", sel, out1);
    sel = 1'b1;
    #5; // select a[1]
    $display("sel=%b === out=%b", sel, out1);

    $display("\nTesting 4 to 1 mux");
    sel4 = 2'b00; 
    #5; // select b[0]
    $display("sel=%b === out=%b", sel4, out2);
    sel4 = 2'b01; 
    #5; // select b[1]
    $display("sel=%b === out=%b", sel4, out2);
    sel4 = 2'b10; 
    #5; // select b[2]
    $display("sel=%b === out=%b", sel4, out2);
    sel4 = 2'b11; 
    #5; // select b[3]
    $display("sel=%b === out=%b", sel4, out2);


    $display("\nTesting 8 to 1 mux");
    sel8 = 3'b000;
    #5; // select c[0]
    $display("sel=%b === out=%b", sel8, out3);

    sel8 = 3'b001;
    #5; // select c[1]
    $display("sel=%b === out=%b", sel8, out3);

    sel8 = 3'b010;
    #5; // select c[2]
    $display("sel=%b === out=%b", sel8, out3);

    sel8 = 3'b011;
    #5; // select c[3]
    $display("sel=%b === out=%b", sel8, out3);

    sel8 = 3'b100;
    #5; // select c[4]
    $display("sel=%b === out=%b", sel8, out3);

    sel8 = 3'b101;
    #5; // select c[5]
    $display("sel=%b === out=%b", sel8, out3);
    
    sel8 = 3'b110;
    #5; // select c[6]
    $display("sel=%b === out=%b", sel8, out3);

    sel8 = 3'b111;
    #5; // select c[7]
    $display("sel=%b === out=%b", sel8, out3);
end 
endmodule

Combinational/muxes/muxes.vcd
$date
	Sat Sep 05 03:32:08 2026
$end
$version
	Icarus Verilog
$end
$timescale
	1ps
$end
$scope module muxtb $end
$var wire 1 ! out3 $end
$var wire 1 " out2 $end
$var wire 1 # out1 $end
$var reg 2 $ a [1:0] $end
$var reg 4 % b [3:0] $end
$var reg 8 & c [7:0] $end
$var reg 1 ' sel $end
$var reg 2 ( sel4 [1:0] $end
$var reg 3 ) sel8 [2:0] $end
$scope module m0 $end
$var wire 1 * a $end
$var wire 1 + b $end
$var wire 1 ' sel $end
$var wire 1 # out $end
$upscope $end
$scope module m1 $end
$var wire 4 , a [3:0] $end
$var wire 2 - sel [1:0] $end
$var reg 1 " out $end
$upscope $end
$scope module m2 $end
$var wire 8 . a [7:0] $end
$var wire 3 / sel [2:0] $end
$var reg 1 ! out $end
$upscope $end
$upscope $end
$enddefinitions $end
$comment Show the parameter values. $end
$dumpall
$end
#0
$dumpvars
bx /
b1010101 .
bx -
b101 ,
0+
1*
bx )
bx (
0'
b1010101 &
b101 %
b1 $
1#
x"
x!
$end
#5000
0#
1'
#10000
1"
b0 (
b0 -
#15000
0"
b1 (
b1 -
#20000
1"
b10 (
b10 -
#25000
0"
b11 (
b11 -
#30000
1!
b0 )
b0 /
#35000
0!
b1 )
b1 /
#40000
1!
b10 )
b10 /
#45000
0!
b11 )
b11 /
#50000
1!
b100 )
b100 /
#55000
0!
b101 )
b101 /
#60000
1!
b110 )
b110 /
#65000
0!
b111 )
b111 /
