Sequential/Register/n_bit_register.v

module n_bit_register #(parameter N = 4)
(
    input [N-1:0] d,
    input clk,
    input rst,
    input en,
    output reg [N-1:0] q
);

always @(posedge clk) begin
    if(rst)
        q <= 0;
    else if (en)
        q <= d;
end
endmodule

Sequential/Shift Registers/PISO.v
//PARALLEL IN SERIAL OUT SHIFT REGISTER
`include "../Register/n_bit_register.v"

module PISO #(parameter N = 4)(
    input [N-1:0] d,
    input clk,
    input SH_LD, // Shift Load: 1 for shift, 0 for load
    input rst,

    output [N-1:0] shift_out,
    output q
);

// to carry the other D forward based on SH_LD
wire [N-2:0] d_in;

//Instantiate the the first d flip flop
n_bit_register #(1) dff0(.d(d[0] & ~SH_LD), .clk(clk), .rst(rst), .q(shift_out[0]), .en(1'b1));

genvar i;

// for loop to generate the remaining D flip-flops
generate
    for (i = 0; i < N - 1; i = i + 1) begin : gen_dff
        // Assign the input to the flip flops based on the shift / load signal
        assign d_in[i] = (shift_out[i] & SH_LD) | (d[i + 1] & ~SH_LD);
        // Instantiate the d flip flops and chain them together with the inputs 
        n_bit_register #(1) dff(.d(d_in[i]), .clk(clk), .rst(rst), .q(shift_out[i + 1]), .en(1'b1));
    end
endgenerate

// Assign the last shift register output to the q output
assign q = shift_out[N-1];

endmodule

Sequential/Shift Registers/PISO_tb.v
`timescale 1ns/1ps
`include "PISO.v"
module PISO_tb;

//inputs 
reg [3:0] d = 0; //intial value
reg clk = 0; 
reg SH_LD = 0;
reg rst = 0; 

//output 
wire q;

//clock generation
always #10 clk = ~clk;

//Instantiate the PISO module
PISO #(.N(4)) piso_inst(.d(d), .clk(clk), .SH_LD(SH_LD), .rst(rst), .q(q));

initial begin

    // Dumping the waveform
    $dumpfile("PISO.vcd");
    $dumpvars(0, PISO_tb);

    $display("PISO Testbench");
    $monitor("d = %b, clk = %b, SH_LD = %b, rst = %b, q = %b", d, clk, SH_LD, rst, q);

    rst = 0; #20 rst = 1; #20 rst = 0; #20 // The reset block
    // load
    d = 4'b1101; SH_LD = 0; #80 
    // shift
    SH_LD = 1; #80
    $finish;
end
    
endmodule

Sequential/Shift Registers/PISO.vcd
$date
	Sun Oct 04 22:54:32 2026
$end
$version
	Icarus Verilog
$end
$timescale
	1ps
$end
$scope module PISO_tb $end
$var wire 1 ! q $end
$var reg 1 " SH_LD $end
$var reg 1 # clk $end
$var reg 4 $ d [3:0] $end
$var reg 1 % rst $end
$scope module piso_inst $end
$var wire 1 " SH_LD $end
$var wire 1 # clk $end
$var wire 4 & d [3:0] $end
$var wire 1 % rst $end
$var wire 4 ' shift_out [3:0] $end
$var wire 1 ! q $end
$var wire 3 ( d_in [2:0] $end
$var parameter 32 ) N $end
$scope begin gen_dff[0] $end
$var parameter 2 * i $end
$scope module dff $end
$var wire 1 # clk $end
$var wire 1 + d $end
$var wire 1 , en $end
$var wire 1 % rst $end
$var parameter 32 - N $end
$var reg 1 . q $end
$upscope $end
$upscope $end
$scope begin gen_dff[1] $end
$var parameter 2 / i $end
$scope module dff $end
$var wire 1 # clk $end
$var wire 1 0 d $end
$var wire 1 1 en $end
$var wire 1 % rst $end
$var parameter 32 2 N $end
$var reg 1 3 q $end
$upscope $end
$upscope $end
$scope begin gen_dff[2] $end
$var parameter 3 4 i $end
$scope module dff $end
$var wire 1 # clk $end
$var wire 1 5 d $end
$var wire 1 6 en $end
$var wire 1 % rst $end
$var parameter 32 7 N $end
$var reg 1 8 q $end
$upscope $end
$upscope $end
$scope module dff0 $end
$var wire 1 # clk $end
$var wire 1 9 d $end
$var wire 1 : en $end
$var wire 1 % rst $end
$var parameter 32 ; N $end
$var reg 1 < q $end
$upscope $end
$upscope $end
$upscope $end
$enddefinitions $end
$comment Show the parameter values. $end
$dumpall
b1 ;
b1 7
b10 4
b1 2
b1 /
b1 -
b0 *
b100 )
$end
#0
$dumpvars
x<
1:
09
x8
16
05
x3
11
00
x.
1,
0+
b0 (
bx '
b0 &
0%
b0 $
0#
0"
x!
$end
#10000
0!
0.
03
08
b0 '
0<
1#
#20000
0#
1%
#30000
1#
#40000
0#
0%
#50000
1#
#60000
10
15
b110 (
19
0#
b1101 $
b1101 &
#70000
1!
1<
18
b1101 '
13
1#
#80000
0#
#90000
1#
#100000
0#
#110000
1#
#120000
0#
#130000
1#
#140000
00
1+
09
b101 (
0#
1"
#150000
0+
05
10
b10 (
0<
03
b1010 '
1.
1#
#160000
0#
#170000
00
15
b100 (
0!
0.
13
b100 '
08
1#
#180000
0#
#190000
05
b0 (
1!
18
b1000 '
03
1#
#200000
0#
#210000
0!
b0 '
08
1#
