Sequential/Shift Registers/SISO.v
//SERIAL IN SERIAL OUT SHIFT REGISTER

module SISO #(parameter N = 1)(
    input d,
    input clk,
    input rst,
    output q,
    output [N-1:0] shift_reg_out
);

reg [N-1:0] shift_reg;

always @(posedge clk) begin
    if(rst)
        shift_reg <= 0; // reset behaviour
    else if (N==1)
        shift_reg <= d; // if N == 1 then make it a simple D flip flop 
    else
        shift_reg <= {shift_reg[N-2:0], d}; // shift the values ahead 
end

assign q = shift_reg[N-1]; // assign the q as the value of the last shift reg
assign shift_reg_out = shift_reg; // assign the output register values
endmodule

Sequential/Shift Registers/SIPO.v
// SERIAL IN PARALLEL OUT SHIFT REGISTER
`include "SISO.v"

module SIPO #(parameter N = 4)
(
    input d,
    input clk,
    input rst,
    output [N-1:0] q
);

// Instiantiate the SISO module
SISO #(N) siso_inst(.d(d), .clk(clk), .rst(rst), .shift_reg_out(q));

endmodule

Sequential/Shift Registers/SIPO_tb.v
`timescale 1ns/1ps
`include "SIPO.v"

module SIPO_tb;

// inputs 
reg d;
reg clk = 0;
reg rst;

// set the clock
always #10 clk = ~clk;

//output, testing for 4 bit case
wire [3:0] q;
wire [3:0] shift_reg_out;

// Instantiate the SIPO module
SIPO #(4) sipo_inst(.d(d), .clk(clk), .rst(rst), .q(q));

initial begin

    //dump the waveform
    $dumpfile("SIPO.vcd");
    $dumpvars(0, SIPO_tb);

    $display("SIPO testbench");
    $monitor("d = %b, rst = %b, q = %b", d, rst, q);

    //test cases
    d = 0; rst = 1; #20;
    d = 0; rst = 0; #20;
    d = 0; #20;
    d = 1; #20;
    d = 0; #80;
    d = 0; #20;
    $finish;

end
endmodule

Sequential/Shift Registers/SIPO.vcd
$date
	Sun Oct 04 18:42:38 2026
$end
$version
	Icarus Verilog
$end
$timescale
	1ps
$end
$scope module SIPO_tb $end
$var wire 4 ! q [3:0] $end
$var reg 1 " clk $end
$var reg 1 # d $end
$var reg 1 $ rst $end
$scope module sipo_inst $end
$var wire 1 " clk $end
$var wire 1 # d $end
$var wire 1 $ rst $end
$var wire 4 % q [3:0] $end
$var parameter 32 & N $end
$scope module siso_inst $end
$var wire 1 " clk $end
$var wire 1 # d $end
$var wire 1 $ rst $end
$var wire 4 ' shift_reg_out [3:0] $end
$var wire 1 ( q $end
$var parameter 32 ) N $end
$var reg 4 * shift_reg [3:0] $end
$upscope $end
$upscope $end
$upscope $end
$enddefinitions $end
$comment Show the parameter values. $end
$dumpall
b100 )
b100 &
$end
#0
$dumpvars
bx *
x(
bx '
bx %
1$
0#
0"
bx !
$end
#10000
0(
b0 !
b0 %
b0 '
b0 *
1"
#20000
0"
0$
#30000
1"
#40000
0"
#50000
1"
#60000
0"
1#
#70000
b1 !
b1 %
b1 '
b1 *
1"
#80000
0"
0#
#90000
b10 !
b10 %
b10 '
b10 *
1"
#100000
0"
#110000
b100 !
b100 %
b100 '
b100 *
1"
#120000
0"
#130000
1(
b1000 !
b1000 %
b1000 '
b1000 *
1"
#140000
0"
#150000
0(
b0 !
b0 %
b0 '
b0 *
1"
