Sequential/Shift Registers/SISO.v
//SERIAL IN SERIAL OUT SHIFT REGISTER

module SISO #(parameter N = 1)(
    input d,
    input clk,
    input rst,
    output q
);

reg [N-1:0] shift_reg;

always @(posedge clk) begin
    if(rst)
        shift_reg <= 0; // reset behaviour
    else if (N==1)
        shift_reg <= d; // if N == 1 then make it a simple D flip flop 
    else
        shift_reg <= {shift_reg[N-2:0], d}; // shift the values ahead 
end

assign q = shift_reg[N-1]; // assign the q as the value of the last shift reg

endmodule

Sequential/Shift Registers/SISO_tb.v
`include "SISO.v"
`timescale 1ns/1ps

module SISO_tb;

//inputs
reg D;
reg clk = 0; //initial value for the clk
reg rst;
parameter N = 4; // 4 bit 

//output
wire q;

// clock pulse 
always #10 clk = ~clk;

// Instantiate a 4 bit SISO shift register
SISO #(.N(N)) s0(.d(D), .clk(clk), .rst(rst), .q(q));

initial begin
    
    //dumping waveform for debugging
    $dumpfile("SISO.vcd");
    $dumpvars(0, SISO_tb);

    $display("SISO testbench");
    $monitor("D=%b clk=%b rst=%b | shift=%b q=%b", D, clk, rst, s0.shift_reg, q);

    //test cases
    D = 0; rst = 1; #20;
    D = 0; rst = 0; #20;
    D = 0; #20;
    D = 1; #20;
    D = 0; #80;
    D = 0; #20;
    $finish;
end

endmodule

Sequential/Shift Registers/SISO.vcd
$date
	Sat Oct 03 15:48:08 2026
$end
$version
	Icarus Verilog
$end
$timescale
	1ps
$end
$scope module SISO_tb $end
$var wire 1 ! q $end
$var parameter 32 " N $end
$var reg 1 # D $end
$var reg 1 $ clk $end
$var reg 1 % rst $end
$scope module s0 $end
$var wire 1 $ clk $end
$var wire 1 # d $end
$var wire 1 % rst $end
$var wire 1 ! q $end
$var parameter 32 & N $end
$var reg 4 ' shift_reg [3:0] $end
$upscope $end
$upscope $end
$enddefinitions $end
$comment Show the parameter values. $end
$dumpall
b100 &
b100 "
$end
#0
$dumpvars
bx '
1%
0$
0#
x!
$end
#10000
0!
b0 '
1$
#20000
0$
0%
#30000
1$
#40000
0$
#50000
1$
#60000
0$
1#
#70000
b1 '
1$
#80000
0$
0#
#90000
b10 '
1$
#100000
0$
#110000
b100 '
1$
#120000
0$
#130000
1!
b1000 '
1$
#140000
0$
#150000
0!
b0 '
1$
